README.md
setup.py
cbase/__init__.py
cbase/__main__.py
cbase/cli.py
cbase/config.py
cbase/main.py
cbase/repo.py
cbase.egg-info/PKG-INFO
cbase.egg-info/SOURCES.txt
cbase.egg-info/dependency_links.txt
cbase.egg-info/entry_points.txt
cbase.egg-info/not-zip-safe
cbase.egg-info/requires.txt
cbase.egg-info/top_level.txt
cbase/utils/__init__.py
cbase/utils/io.py
cbase/utils/misc.py