Metadata-Version: 2.1
Name: cbase
Version: 0.0.1
Summary: Collective Knowledge DataBase
Home-page: https://github.com/gfursin/cbase
Author: Grigori Fursin
Author-email: gfursin@gmail.com
License: Apache 2.0
Keywords: ck,database,code,data,reuse,common api
Platform: UNKNOWN
Classifier: Development Status :: 1 - Planning
Classifier: License :: OSI Approved :: Apache Software License
Classifier: Programming Language :: Python
Classifier: Intended Audience :: Developers
